zapient/__init__.py
zapient-0.0.0.dist-info/METADATA
zapient-0.0.0.dist-info/WHEEL
zapient-0.0.0.dist-info/RECORD
