Metadata-Version: 2.4
Name: zapient
Version: 0.0.0
Summary: Lightweight web stack
Project-URL: Source, https://github.com/zensical/zapient
License: MIT
